README.rst
setup.py
translate.py
test/test.py
test/test_baidu.py
test/test_bing.py
test/test_google.py
translate_html.egg-info/PKG-INFO
translate_html.egg-info/SOURCES.txt
translate_html.egg-info/dependency_links.txt
translate_html.egg-info/entry_points.txt
translate_html.egg-info/requires.txt
translate_html.egg-info/top_level.txt
translate_html.egg-info/zip-safe