Metadata-Version: 1.1
Name: translate-html
Version: 1.2.4
Summary: translate html to chinese without tag. 
Home-page: https://github.com/ShichaoMa/translate_html
Author: cn
Author-email: cnaafhvk@foxmail.com
License: MIT
Keywords: translate html chinese tag
Platform: UNKNOWN
Classifier: License :: OSI Approved :: MIT License
Classifier: Programming Language :: Python
Classifier: Intended Audience :: Developers
Classifier: Operating System :: OS Independent
